omh/__about__.py
omh/__init__.py
omh/constants.py
omh/core.py
omh/decor.py
omh/fn.py
omh/utils.py
omh/contrib/__init__.py
omh/contrib/entail.py
omh/contrib/motivate.py
omh/contrib/sentiment.py
omh/contrib/summarize.py
omh/contrib/wiki_link.py
omh/contrib/writing/__init__.py
omh/contrib/writing/essay.py
omh/contrib/writing/grammar.py
omh/impl/__init__.py
omh/impl/openai.py
omh-0.0.2.dist-info/METADATA
omh-0.0.2.dist-info/WHEEL
omh-0.0.2.dist-info/licenses/LICENSE.txt
omh-0.0.2.dist-info/RECORD
