Metadata-Version: 2.3
Name: omh
Version: 0.0.2
Project-URL: Documentation, https://github.com/dataset-sh/omh#readme
Project-URL: Issues, https://github.com/dataset-sh/omh/issues
Project-URL: Source, https://github.com/dataset-sh/omh
Author-email: Hao Wu <haowu@dataset.sh>
License: MIT
Classifier: Development Status :: 4 - Beta
Classifier: Programming Language :: Python
Classifier: Programming Language :: Python :: 3.8
Classifier: Programming Language :: Python :: 3.9
Classifier: Programming Language :: Python :: 3.10
Classifier: Programming Language :: Python :: 3.11
Classifier: Programming Language :: Python :: 3.12
Classifier: Programming Language :: Python :: Implementation :: CPython
Classifier: Programming Language :: Python :: Implementation :: PyPy
Requires-Python: >=3.8
Requires-Dist: cmfn~=0.0.2
Requires-Dist: openai
